odoo10_addon_account_tag_category-10.0.1.0.0.99.dev35-py3.8-nspkg.pth
odoo/addons/account_tag_category/README.rst
odoo/addons/account_tag_category/__init__.py
odoo/addons/account_tag_category/__manifest__.py
odoo/addons/account_tag_category/i18n/account_tag_category.pot
odoo/addons/account_tag_category/i18n/am.po
odoo/addons/account_tag_category/i18n/ar.po
odoo/addons/account_tag_category/i18n/bg.po
odoo/addons/account_tag_category/i18n/bs.po
odoo/addons/account_tag_category/i18n/ca.po
odoo/addons/account_tag_category/i18n/cs.po
odoo/addons/account_tag_category/i18n/da.po
odoo/addons/account_tag_category/i18n/de.po
odoo/addons/account_tag_category/i18n/el_GR.po
odoo/addons/account_tag_category/i18n/en_GB.po
odoo/addons/account_tag_category/i18n/es.po
odoo/addons/account_tag_category/i18n/es_AR.po
odoo/addons/account_tag_category/i18n/es_CL.po
odoo/addons/account_tag_category/i18n/es_CO.po
odoo/addons/account_tag_category/i18n/es_CR.po
odoo/addons/account_tag_category/i18n/es_DO.po
odoo/addons/account_tag_category/i18n/es_EC.po
odoo/addons/account_tag_category/i18n/es_ES.po
odoo/addons/account_tag_category/i18n/es_MX.po
odoo/addons/account_tag_category/i18n/es_PE.po
odoo/addons/account_tag_category/i18n/es_PY.po
odoo/addons/account_tag_category/i18n/es_VE.po
odoo/addons/account_tag_category/i18n/et.po
odoo/addons/account_tag_category/i18n/eu.po
odoo/addons/account_tag_category/i18n/fa.po
odoo/addons/account_tag_category/i18n/fi.po
odoo/addons/account_tag_category/i18n/fr.po
odoo/addons/account_tag_category/i18n/fr_CA.po
odoo/addons/account_tag_category/i18n/fr_CH.po
odoo/addons/account_tag_category/i18n/gl.po
odoo/addons/account_tag_category/i18n/gl_ES.po
odoo/addons/account_tag_category/i18n/gu.po
odoo/addons/account_tag_category/i18n/he.po
odoo/addons/account_tag_category/i18n/hr.po
odoo/addons/account_tag_category/i18n/hr_HR.po
odoo/addons/account_tag_category/i18n/hu.po
odoo/addons/account_tag_category/i18n/id.po
odoo/addons/account_tag_category/i18n/it.po
odoo10_addon_account_tag_category-10.0.1.0.0.99.dev35.dist-info/METADATA
odoo10_addon_account_tag_category-10.0.1.0.0.99.dev35.dist-info/WHEEL
odoo10_addon_account_tag_category-10.0.1.0.0.99.dev35.dist-info/namespace_packages.txt
odoo10_addon_account_tag_category-10.0.1.0.0.99.dev35.dist-info/top_level.txt
odoo10_addon_account_tag_category-10.0.1.0.0.99.dev35.dist-info/RECORD
