Metadata-Version: 2.1
Name: odoo10-addon-account-tag-category
Version: 10.0.1.0.0.99.dev35
Summary: Group account tags by categories
Home-page: https://www.camptocamp.com/
Author: Camptocamp SA,Odoo Community Association (OCA)
Author-email: support@odoo-community.org
License: AGPL-3
Platform: UNKNOWN
Classifier: Programming Language :: Python
Classifier: Framework :: Odoo
Classifier: Framework :: Odoo :: 10.0
Classifier: License :: OSI Approved :: GNU Affero General Public License v3
Requires-Python: ~=2.7
Requires-Dist: odoo10-addon-web-m2x-options
Requires-Dist: odoo (<10.1dev,>=10.0)
